{
  "n": 50,
  "weights": [
    100,
    70,
    33,
    89,
    60,
    77,
    43,
    97,
    83,
    3,
    86,
    92,
    85,
    41,
    82,
    38,
    46,
    55,
    13,
    44,
    72,
    41,
    38,
    16,
    3,
    35,
    95,
    69,
    49,
    1,
    13,
    96,
    67,
    15,
    74,
    21,
    36,
    10,
    96,
    15,
    95,
    89,
    95,
    60,
    68,
    46,
    68,
    39,
    10,
    6
  ],
  "profits": [
    12,
    78,
    6,
    72,
    37,
    58,
    22,
    90,
    99,
    57,
    9,
    83,
    58,
    21,
    90,
    27,
    66,
    29,
    65,
    73,
    76,
    91,
    17,
    95,
    78,
    49,
    52,
    28,
    40,
    20,
    29,
    78,
    27,
    64,
    20,
    24,
    31,
    43,
    25,
    43,
    66,
    25,
    53,
    66,
    30,
    99,
    4,
    22,
    8,
    9
  ],
  "capacity": 1337,
  "optimal": 1840,
  "seed": 9886237
}